EduDraw/__init__.py
EduDraw/edudraw.py
EduDraw/requirements.txt
edudraw-1.4.1.dist-info/METADATA
edudraw-1.4.1.dist-info/WHEEL
edudraw-1.4.1.dist-info/licenses/LICENSE
edudraw-1.4.1.dist-info/RECORD
