Metadata-Version: 2.1
Name: EduDraw
Version: 1.4.1
Summary: A simple interface for using 2D graphics in python
Project-URL: Homepage, https://github.com/MuriloLCN/Edu-Draw-Python
Project-URL: Bug Tracker, https://github.com/MuriloLCN/Edu-Draw-Python/issues
Author-email: Murilo Luis Calvo Neves <muriloluiscalvoneves2004@hotmail.com>
License-File: LICENSE
Classifier: License :: OSI Approved :: GNU Lesser General Public License v2 or later (LGPLv2+)
Classifier: Operating System :: OS Independent
Classifier: Programming Language :: Python :: 3
Requires-Python: >=3.7
